twitter.common.rwbuf-0.3.11-py2.7-nspkg.pth
twitter/common/rwbuf/__init__.py
twitter/common/rwbuf/read_write_buffer.py
twitter.common.rwbuf-0.3.11.dist-info/DESCRIPTION.rst
twitter.common.rwbuf-0.3.11.dist-info/METADATA
twitter.common.rwbuf-0.3.11.dist-info/RECORD
twitter.common.rwbuf-0.3.11.dist-info/WHEEL
twitter.common.rwbuf-0.3.11.dist-info/metadata.json
twitter.common.rwbuf-0.3.11.dist-info/namespace_packages.txt
twitter.common.rwbuf-0.3.11.dist-info/top_level.txt
twitter.common.rwbuf-0.3.11.dist-info/zip-safe
